kvdn_client/__init__.py
kvdn_client/__main__.py
kvdn_client/kvdn_client.py
kvdn_pillar/kvdn.py
kvdnc-2.13.dist-info/DESCRIPTION.rst
kvdnc-2.13.dist-info/METADATA
kvdnc-2.13.dist-info/RECORD
kvdnc-2.13.dist-info/WHEEL
kvdnc-2.13.dist-info/entry_points.txt
kvdnc-2.13.dist-info/metadata.json
kvdnc-2.13.dist-info/top_level.txt
