Metadata-Version: 2.0
Name: kvdnc
Version: 2.13
Summary: kvdn client library and tool
Home-page: UNKNOWN
Author: Grant Haywood
Author-email: UNKNOWN
License: Apache
Platform: UNKNOWN
Classifier: Programming Language :: Python
Classifier: Programming Language :: Python :: 2.7
Classifier: Programming Language :: Python :: 3.6
Requires-Dist: requests
Requires-Dist: six
Requires-Dist: argparse
Requires-Dist: sqlitedict
